easyrag/__init__.py
easyrag/runner.py
easyrag/utils.py
easyrag/metrics/__init__.py
easyrag/metrics/answer_correctness.py
easyrag/metrics/answer_faithfulness.py
easyrag/metrics/context_precision.py
easyrag/metrics/context_recall.py
easyrag-0.0.1.dist-info/METADATA
easyrag-0.0.1.dist-info/WHEEL
easyrag-0.0.1.dist-info/licenses/LICENSE
easyrag-0.0.1.dist-info/RECORD
