Metadata-Version: 2.1
Name: easyrag
Version: 0.0.1
Summary: Description
Project-URL: Documentation, https://github.com/unknown/hatch-demo#readme
Project-URL: Issues, https://github.com/unknown/hatch-demo/issues
Project-URL: Source, https://github.com/unknown/hatch-demo
Author-email: Philipp Schmid <schmidphilipp1995@gmail.com>
License-Expression: MIT
License-File: LICENSE
Classifier: Intended Audience :: Developers
Classifier: License :: OSI Approved :: MIT License
Classifier: Programming Language :: Python :: 3 :: Only
Classifier: Programming Language :: Python :: 3.10
Classifier: Topic :: Internet
Classifier: Topic :: Software Development
Classifier: Topic :: Software Development :: Libraries
Classifier: Topic :: Software Development :: Libraries :: Application Frameworks
Classifier: Topic :: Software Development :: Libraries :: Python Modules
Requires-Python: >=3.8
Requires-Dist: asyncio
Requires-Dist: huggingface-hub
Requires-Dist: langchain==0.1.9
Requires-Dist: langgraph
Requires-Dist: nest-asyncio
